{"id":"ba665c75-61e1-4328-b7d0-20fb5b6fbdd2","timestamp":1767490127476,"matcher":{"static":{},"wildcard":{},"dynamic":{}},"prerendered":["/","/donate","/sha512","/sha384","/sha256","/hmacripemd160","/tripledes","/hmacsha224","/ripemd160","/rabbit","/des","/hmacsha256","/base64","/pbkdf2","/hmacmd5","/rc4","/hmacsha384","/rc4drop","/hmacsha512","/sha3","/decodetx","/aes","/encoder","/hmacsha1","/qrcodemul","/tetris","/hex","/tontools","/qrcode","/sha1","/sha224","/pic2base64","/jsonformat","/life","/chscht","/qrcodereader","/xrptools","/microsofttranslate","/md5","/adatools","/abidecoder","/contract_evm"]}